Metadata-Version: 2.1
Name: mynameisWS
Version: 0.0.2
Summary: What is WS
Home-page: https://github.com/PalmWS/mynameisWS
Download-URL: https://github.com/PalmWS/mynameisWS
Author: Wise System
Author-email: test@gmail.com
License: MIT
Keywords: WS,Wise System,ASCII ART
Classifier: Development Status :: 3 - Alpha
Classifier: Intended Audience :: Education
Classifier: Topic :: Utilities
Classifier: License :: OSI Approved :: MIT License
Classifier: Programming Language :: Python :: 3
Classifier: Programming Language :: Python :: 3.4
Classifier: Programming Language :: Python :: 3.5
Classifier: Programming Language :: Python :: 3.6
Classifier: Programming Language :: Python :: 3.7
Classifier: Programming Language :: Python :: 3.8
Classifier: Programming Language :: Python :: 3.9
Classifier: Programming Language :: Python :: 3.10
License-File: LICENSE
License-File: LICENSE.txt
